corvette/__init__.py
corvette-0.0.1.dist-info/LICENSE
corvette-0.0.1.dist-info/METADATA
corvette-0.0.1.dist-info/WHEEL
corvette-0.0.1.dist-info/top_level.txt
corvette-0.0.1.dist-info/RECORD
