Metadata-Version: 2.1
Name: corvette
Version: 0.0.1
Summary: An autoindex static site generator for directory listings
Home-page: https://github.com/philipkiely/corvette
Author: Philip Kiely
Author-email: philip@kiely.xyz
License: UNKNOWN
Platform: UNKNOWN
Classifier: Programming Language :: Python :: 3
Classifier: License :: OSI Approved :: MIT License
Classifier: Operating System :: OS Independent
Requires-Python: >=3.6
